README.rst
setup.py
Lysidike.egg-info/PKG-INFO
Lysidike.egg-info/SOURCES.txt
Lysidike.egg-info/dependency_links.txt
Lysidike.egg-info/entry_points.txt
Lysidike.egg-info/requires.txt
Lysidike.egg-info/top_level.txt
lysidike/__init__.py
lysidike/publishgateway.py
lysidike/schema/__init__.py
lysidike/schema/emailservice.py
lysidike/schema/publishgateway.py
lysidike/schema/servicefactory.py
lysidike/schema/stdoutservice.py
lysidike/schema/task.py
lysidike/services/__init__.py
lysidike/services/aservice.py
lysidike/services/emailservice.py
lysidike/services/servicefactory.py
lysidike/services/stdoutservice.py
lysidike/tasks/__init__.py
lysidike/tasks/task.py
lysidike/tasks/taskfactory.py
tests_unit/__init__.py
tests_unit/test_email.py
tests_unit/test_publishgateway.py
tests_unit/test_servicefactory.py
tests_unit/test_stdout.py
tests_unit/test_task.py
tests_unit/test_taskfactory.py
tests_unit/test_validateconfig.py